Metadata-Version: 1.0
Name: pdfconduit-gui
Version: 0.3.1
Summary: GUI wrapper for pdfconduit.
Home-page: https://github.com/mrstephenneal/pdfconduit
Author: Stephen Neal
Author-email: stephen@stephenneal.net
License: UNKNOWN
Platform: UNKNOWN
